MANIFEST.in
setup.py
anthill/admin/__init__.py
anthill/admin/handler.py
anthill/admin/options.py
anthill/admin/server.py
anthill/admin/model/__init__.py
anthill/admin/model/admin.py
anthill/admin/model/audit.py
anthill/admin/sql/audit_log.sql
anthill/admin/static/css/animate.css
anthill/admin/static/css/bootstrap-datetimepicker.min.css
anthill/admin/static/css/bootstrap-select.min.css
anthill/admin/static/css/bootstrap-switch.min.css
anthill/admin/static/css/bootstrap-tagsinput.css
anthill/admin/static/css/bootstrap.css
anthill/admin/static/css/codeflask.css
anthill/admin/static/css/codemirror.css
anthill/admin/static/css/font-awesome.min.css
anthill/admin/static/css/jsoneditor.min.css
anthill/admin/static/css/open-sans.css
anthill/admin/static/css/prism.css
anthill/admin/static/css/sandbox.css
anthill/admin/static/css/show-hint.css
anthill/admin/static/css/style.css
anthill/admin/static/css/themes/idle.css
anthill/admin/static/fonts/FontAwesome.otf
anthill/admin/static/fonts/fontawesome-webfont.eot
anthill/admin/static/fonts/fontawesome-webfont.svg
anthill/admin/static/fonts/fontawesome-webfont.ttf
anthill/admin/static/fonts/fontawesome-webfont.woff
anthill/admin/static/fonts/fontawesome-webfont.woff2
anthill/admin/static/fonts/glyphicons-halflings-regular.eot
anthill/admin/static/fonts/glyphicons-halflings-regular.svg
anthill/admin/static/fonts/glyphicons-halflings-regular.ttf
anthill/admin/static/fonts/glyphicons-halflings-regular.woff
anthill/admin/static/fonts/glyphicons-halflings-regular.woff2
anthill/admin/static/fonts/opensans/59ZRklaO5bWGqF5A9baEEYX0hVgzZQUfRDuZrPvH3D8.woff2
anthill/admin/static/fonts/opensans/K88pR3goAWT7BTt32Z01m4X0hVgzZQUfRDuZrPvH3D8.woff2
anthill/admin/static/fonts/opensans/LWCjsQkB6EMdfHrEVqA1KYX0hVgzZQUfRDuZrPvH3D8.woff2
anthill/admin/static/fonts/opensans/RjgO7rYTmqiVp7vzi-Q5UYX0hVgzZQUfRDuZrPvH3D8.woff2
anthill/admin/static/fonts/opensans/cJZKeOuBrn4kERxqtaUH3ZBw1xU1rKptJj_0jans920.woff2
anthill_admin.egg-info/PKG-INFO
anthill_admin.egg-info/SOURCES.txt
anthill_admin.egg-info/dependency_links.txt
anthill_admin.egg-info/namespace_packages.txt
anthill_admin.egg-info/not-zip-safe
anthill_admin.egg-info/requires.txt
anthill_admin.egg-info/top_level.txt