Metadata-Version: 1.0
Name: anthill-admin
Version: 0.2
Summary: Administration service for Anthill Platform
Home-page: https://github.com/anthill-platform/anthill-admin
Author: desertkun
Author-email: desertkun@gmail.com
License: MIT
Platform: UNKNOWN
